CHANGES.txt
LICENSE.txt
MANIFEST.in
README.rst
requirements-dev.txt
requirements-testing.txt
setup.py
django_dumper.egg-info/PKG-INFO
django_dumper.egg-info/SOURCES.txt
django_dumper.egg-info/dependency_links.txt
django_dumper.egg-info/requires.txt
django_dumper.egg-info/top_level.txt
dumper/__init__.py
dumper/invalidation.py
dumper/logging_utils.py
dumper/middleware.py
dumper/settings.py
dumper/site.py
dumper/utils.py
test/__init__.py
test/models.py
test/settings.py
test/test_full_stack.py
test/test_invalidation.py
test/test_logging_utils.py
test/test_site.py
test/test_utils.py
test/urls.py
test/utils.py
test/views.py